ymw16.so
pyymw16/__init__.py
pyymw16/spiral.txt
pyymw16/ymw16par.txt
pyymw16-2.0.7.dist-info/METADATA
pyymw16-2.0.7.dist-info/WHEEL
pyymw16-2.0.7.dist-info/top_level.txt
pyymw16-2.0.7.dist-info/RECORD
