Metadata-Version: 2.1
Name: pyymw16
Version: 2.0.7
Summary: Python/C++ version of YMW16 electron density model
Home-page: https://github.com/telegraphic/pyymw16
Author: D. Price
Author-email: dancpr@berkeley.edu
License: UNKNOWN
Download-URL: https://github.com/telegraphic/pyymw16/archive/2.0.7.tar.gz
Platform: UNKNOWN
Requires-Python: >=2.7
Requires-Dist: pybind11 (>=2.2)
Requires-Dist: astropy (<3.0)
